{
  "resourceName": "Bundle_Request",
  "attr_character_encoding": {
    "Bundle_Request._method": "utf-8",
    "Bundle_Request.url": "utf-8",
    "Bundle_Request._ifMatch": "utf-8",
    "Bundle_Request.extension": "utf-8",
    "Bundle_Request.modifierExtension": "utf-8",
    "Bundle_Request._url": "utf-8",
    "Bundle_Request.ifNoneMatch": "utf-8",
    "Bundle_Request.ifNoneExist": "utf-8",
    "Bundle_Request._ifNoneExist": "utf-8",
    "Bundle_Request.id": "utf-8",
    "Bundle_Request.method": "utf-8",
    "Bundle_Request.ifModifiedSince": "utf-8",
    "Bundle_Request._ifModifiedSince": "utf-8",
    "Bundle_Request._ifNoneMatch": "utf-8",
    "Bundle_Request.ifMatch": "utf-8"
  }
}